{ "@timestamp": "2026-03-15T13:44:30.831187", "key": "Running XVA Analytic", "progress": 0, "total": 1 }
{ "@timestamp": "2026-03-15T13:44:30.831574", "key": "XVA: Build Today's Market", "progress": 0, "total": 1 }
{ "@timestamp": "2026-03-15T13:44:30.932463", "key": "XVA: Build Today's Market", "progress": 1, "total": 1 }
{ "@timestamp": "2026-03-15T13:44:31.371068", "key": "XVA: Build Portfolio", "progress": 0, "total": 1 }
{ "@timestamp": "2026-03-15T13:44:31.376806", "key": "XVA: Build Portfolio", "progress": 1, "total": 1 }
{ "@timestamp": "2026-03-15T13:44:31.517485", "detail": "1 trade, 1000 samples", "key": "XVA: Building cube", "progress": 0, "total": 1000 }
{ "@timestamp": "2026-03-15T13:44:31.763371", "detail": "1 trade, 1000 samples", "key": "XVA: Building cube", "progress": 10, "total": 1000 }
{ "@timestamp": "2026-03-15T13:44:32.008538", "detail": "1 trade, 1000 samples", "key": "XVA: Building cube", "progress": 20, "total": 1000 }
{ "@timestamp": "2026-03-15T13:44:32.252977", "detail": "1 trade, 1000 samples", "key": "XVA: Building cube", "progress": 30, "total": 1000 }
{ "@timestamp": "2026-03-15T13:44:32.500029", "detail": "1 trade, 1000 samples", "key": "XVA: Building cube", "progress": 40, "total": 1000 }
{ "@timestamp": "2026-03-15T13:44:32.745490", "detail": "1 trade, 1000 samples", "key": "XVA: Building cube", "progress": 50, "total": 1000 }
{ "@timestamp": "2026-03-15T13:44:32.989505", "detail": "1 trade, 1000 samples", "key": "XVA: Building cube", "progress": 60, "total": 1000 }
{ "@timestamp": "2026-03-15T13:44:33.234692", "detail": "1 trade, 1000 samples", "key": "XVA: Building cube", "progress": 70, "total": 1000 }
{ "@timestamp": "2026-03-15T13:44:33.479966", "detail": "1 trade, 1000 samples", "key": "XVA: Building cube", "progress": 80, "total": 1000 }
{ "@timestamp": "2026-03-15T13:44:33.726849", "detail": "1 trade, 1000 samples", "key": "XVA: Building cube", "progress": 90, "total": 1000 }
{ "@timestamp": "2026-03-15T13:44:33.972418", "detail": "1 trade, 1000 samples", "key": "XVA: Building cube", "progress": 100, "total": 1000 }
{ "@timestamp": "2026-03-15T13:44:34.219307", "detail": "1 trade, 1000 samples", "key": "XVA: Building cube", "progress": 110, "total": 1000 }
{ "@timestamp": "2026-03-15T13:44:34.465305", "detail": "1 trade, 1000 samples", "key": "XVA: Building cube", "progress": 120, "total": 1000 }
{ "@timestamp": "2026-03-15T13:44:34.710543", "detail": "1 trade, 1000 samples", "key": "XVA: Building cube", "progress": 130, "total": 1000 }
{ "@timestamp": "2026-03-15T13:44:34.954460", "detail": "1 trade, 1000 samples", "key": "XVA: Building cube", "progress": 140, "total": 1000 }
{ "@timestamp": "2026-03-15T13:44:35.199130", "detail": "1 trade, 1000 samples", "key": "XVA: Building cube", "progress": 150, "total": 1000 }
{ "@timestamp": "2026-03-15T13:44:35.444181", "detail": "1 trade, 1000 samples", "key": "XVA: Building cube", "progress": 160, "total": 1000 }
{ "@timestamp": "2026-03-15T13:44:35.690075", "detail": "1 trade, 1000 samples", "key": "XVA: Building cube", "progress": 170, "total": 1000 }
{ "@timestamp": "2026-03-15T13:44:35.932836", "detail": "1 trade, 1000 samples", "key": "XVA: Building cube", "progress": 180, "total": 1000 }
{ "@timestamp": "2026-03-15T13:44:36.177419", "detail": "1 trade, 1000 samples", "key": "XVA: Building cube", "progress": 190, "total": 1000 }
{ "@timestamp": "2026-03-15T13:44:36.421937", "detail": "1 trade, 1000 samples", "key": "XVA: Building cube", "progress": 200, "total": 1000 }
{ "@timestamp": "2026-03-15T13:44:36.665433", "detail": "1 trade, 1000 samples", "key": "XVA: Building cube", "progress": 210, "total": 1000 }
{ "@timestamp": "2026-03-15T13:44:36.918792", "detail": "1 trade, 1000 samples", "key": "XVA: Building cube", "progress": 220, "total": 1000 }
{ "@timestamp": "2026-03-15T13:44:37.185418", "detail": "1 trade, 1000 samples", "key": "XVA: Building cube", "progress": 230, "total": 1000 }
{ "@timestamp": "2026-03-15T13:44:37.451582", "detail": "1 trade, 1000 samples", "key": "XVA: Building cube", "progress": 240, "total": 1000 }
{ "@timestamp": "2026-03-15T13:44:37.703764", "detail": "1 trade, 1000 samples", "key": "XVA: Building cube", "progress": 250, "total": 1000 }
{ "@timestamp": "2026-03-15T13:44:37.954783", "detail": "1 trade, 1000 samples", "key": "XVA: Building cube", "progress": 260, "total": 1000 }
{ "@timestamp": "2026-03-15T13:44:38.204342", "detail": "1 trade, 1000 samples", "key": "XVA: Building cube", "progress": 270, "total": 1000 }
{ "@timestamp": "2026-03-15T13:44:38.455889", "detail": "1 trade, 1000 samples", "key": "XVA: Building cube", "progress": 280, "total": 1000 }
{ "@timestamp": "2026-03-15T13:44:38.703323", "detail": "1 trade, 1000 samples", "key": "XVA: Building cube", "progress": 290, "total": 1000 }
{ "@timestamp": "2026-03-15T13:44:38.947054", "detail": "1 trade, 1000 samples", "key": "XVA: Building cube", "progress": 300, "total": 1000 }
{ "@timestamp": "2026-03-15T13:44:39.193233", "detail": "1 trade, 1000 samples", "key": "XVA: Building cube", "progress": 310, "total": 1000 }
{ "@timestamp": "2026-03-15T13:44:39.437304", "detail": "1 trade, 1000 samples", "key": "XVA: Building cube", "progress": 320, "total": 1000 }
{ "@timestamp": "2026-03-15T13:44:39.682157", "detail": "1 trade, 1000 samples", "key": "XVA: Building cube", "progress": 330, "total": 1000 }
{ "@timestamp": "2026-03-15T13:44:39.926863", "detail": "1 trade, 1000 samples", "key": "XVA: Building cube", "progress": 340, "total": 1000 }
{ "@timestamp": "2026-03-15T13:44:40.173406", "detail": "1 trade, 1000 samples", "key": "XVA: Building cube", "progress": 350, "total": 1000 }
{ "@timestamp": "2026-03-15T13:44:40.418348", "detail": "1 trade, 1000 samples", "key": "XVA: Building cube", "progress": 360, "total": 1000 }
{ "@timestamp": "2026-03-15T13:44:40.666571", "detail": "1 trade, 1000 samples", "key": "XVA: Building cube", "progress": 370, "total": 1000 }
{ "@timestamp": "2026-03-15T13:44:40.911154", "detail": "1 trade, 1000 samples", "key": "XVA: Building cube", "progress": 380, "total": 1000 }
{ "@timestamp": "2026-03-15T13:44:41.157627", "detail": "1 trade, 1000 samples", "key": "XVA: Building cube", "progress": 390, "total": 1000 }
{ "@timestamp": "2026-03-15T13:44:41.402196", "detail": "1 trade, 1000 samples", "key": "XVA: Building cube", "progress": 400, "total": 1000 }
{ "@timestamp": "2026-03-15T13:44:41.649164", "detail": "1 trade, 1000 samples", "key": "XVA: Building cube", "progress": 410, "total": 1000 }
{ "@timestamp": "2026-03-15T13:44:41.899428", "detail": "1 trade, 1000 samples", "key": "XVA: Building cube", "progress": 420, "total": 1000 }
{ "@timestamp": "2026-03-15T13:44:42.147636", "detail": "1 trade, 1000 samples", "key": "XVA: Building cube", "progress": 430, "total": 1000 }
{ "@timestamp": "2026-03-15T13:44:42.404194", "detail": "1 trade, 1000 samples", "key": "XVA: Building cube", "progress": 440, "total": 1000 }
{ "@timestamp": "2026-03-15T13:44:42.654125", "detail": "1 trade, 1000 samples", "key": "XVA: Building cube", "progress": 450, "total": 1000 }
{ "@timestamp": "2026-03-15T13:44:42.902992", "detail": "1 trade, 1000 samples", "key": "XVA: Building cube", "progress": 460, "total": 1000 }
{ "@timestamp": "2026-03-15T13:44:43.150750", "detail": "1 trade, 1000 samples", "key": "XVA: Building cube", "progress": 470, "total": 1000 }
{ "@timestamp": "2026-03-15T13:44:43.399099", "detail": "1 trade, 1000 samples", "key": "XVA: Building cube", "progress": 480, "total": 1000 }
{ "@timestamp": "2026-03-15T13:44:43.646681", "detail": "1 trade, 1000 samples", "key": "XVA: Building cube", "progress": 490, "total": 1000 }
{ "@timestamp": "2026-03-15T13:44:43.895225", "detail": "1 trade, 1000 samples", "key": "XVA: Building cube", "progress": 500, "total": 1000 }
{ "@timestamp": "2026-03-15T13:44:44.144792", "detail": "1 trade, 1000 samples", "key": "XVA: Building cube", "progress": 510, "total": 1000 }
{ "@timestamp": "2026-03-15T13:44:44.393089", "detail": "1 trade, 1000 samples", "key": "XVA: Building cube", "progress": 520, "total": 1000 }
{ "@timestamp": "2026-03-15T13:44:44.640298", "detail": "1 trade, 1000 samples", "key": "XVA: Building cube", "progress": 530, "total": 1000 }
{ "@timestamp": "2026-03-15T13:44:44.888531", "detail": "1 trade, 1000 samples", "key": "XVA: Building cube", "progress": 540, "total": 1000 }
{ "@timestamp": "2026-03-15T13:44:45.136140", "detail": "1 trade, 1000 samples", "key": "XVA: Building cube", "progress": 550, "total": 1000 }
{ "@timestamp": "2026-03-15T13:44:45.385151", "detail": "1 trade, 1000 samples", "key": "XVA: Building cube", "progress": 560, "total": 1000 }
{ "@timestamp": "2026-03-15T13:44:45.633769", "detail": "1 trade, 1000 samples", "key": "XVA: Building cube", "progress": 570, "total": 1000 }
{ "@timestamp": "2026-03-15T13:44:45.882077", "detail": "1 trade, 1000 samples", "key": "XVA: Building cube", "progress": 580, "total": 1000 }
{ "@timestamp": "2026-03-15T13:44:46.131124", "detail": "1 trade, 1000 samples", "key": "XVA: Building cube", "progress": 590, "total": 1000 }
{ "@timestamp": "2026-03-15T13:44:46.378039", "detail": "1 trade, 1000 samples", "key": "XVA: Building cube", "progress": 600, "total": 1000 }
{ "@timestamp": "2026-03-15T13:44:46.627331", "detail": "1 trade, 1000 samples", "key": "XVA: Building cube", "progress": 610, "total": 1000 }
{ "@timestamp": "2026-03-15T13:44:46.874796", "detail": "1 trade, 1000 samples", "key": "XVA: Building cube", "progress": 620, "total": 1000 }
{ "@timestamp": "2026-03-15T13:44:47.124038", "detail": "1 trade, 1000 samples", "key": "XVA: Building cube", "progress": 630, "total": 1000 }
{ "@timestamp": "2026-03-15T13:44:47.371379", "detail": "1 trade, 1000 samples", "key": "XVA: Building cube", "progress": 640, "total": 1000 }
{ "@timestamp": "2026-03-15T13:44:47.619884", "detail": "1 trade, 1000 samples", "key": "XVA: Building cube", "progress": 650, "total": 1000 }
{ "@timestamp": "2026-03-15T13:44:47.868117", "detail": "1 trade, 1000 samples", "key": "XVA: Building cube", "progress": 660, "total": 1000 }
{ "@timestamp": "2026-03-15T13:44:48.115998", "detail": "1 trade, 1000 samples", "key": "XVA: Building cube", "progress": 670, "total": 1000 }
{ "@timestamp": "2026-03-15T13:44:48.363220", "detail": "1 trade, 1000 samples", "key": "XVA: Building cube", "progress": 680, "total": 1000 }
{ "@timestamp": "2026-03-15T13:44:48.610606", "detail": "1 trade, 1000 samples", "key": "XVA: Building cube", "progress": 690, "total": 1000 }
{ "@timestamp": "2026-03-15T13:44:48.857942", "detail": "1 trade, 1000 samples", "key": "XVA: Building cube", "progress": 700, "total": 1000 }
{ "@timestamp": "2026-03-15T13:44:49.105704", "detail": "1 trade, 1000 samples", "key": "XVA: Building cube", "progress": 710, "total": 1000 }
{ "@timestamp": "2026-03-15T13:44:49.354067", "detail": "1 trade, 1000 samples", "key": "XVA: Building cube", "progress": 720, "total": 1000 }
{ "@timestamp": "2026-03-15T13:44:49.603732", "detail": "1 trade, 1000 samples", "key": "XVA: Building cube", "progress": 730, "total": 1000 }
{ "@timestamp": "2026-03-15T13:44:49.856320", "detail": "1 trade, 1000 samples", "key": "XVA: Building cube", "progress": 740, "total": 1000 }
{ "@timestamp": "2026-03-15T13:44:50.106080", "detail": "1 trade, 1000 samples", "key": "XVA: Building cube", "progress": 750, "total": 1000 }
{ "@timestamp": "2026-03-15T13:44:50.355689", "detail": "1 trade, 1000 samples", "key": "XVA: Building cube", "progress": 760, "total": 1000 }
{ "@timestamp": "2026-03-15T13:44:50.606118", "detail": "1 trade, 1000 samples", "key": "XVA: Building cube", "progress": 770, "total": 1000 }
{ "@timestamp": "2026-03-15T13:44:50.856130", "detail": "1 trade, 1000 samples", "key": "XVA: Building cube", "progress": 780, "total": 1000 }
{ "@timestamp": "2026-03-15T13:44:51.106208", "detail": "1 trade, 1000 samples", "key": "XVA: Building cube", "progress": 790, "total": 1000 }
{ "@timestamp": "2026-03-15T13:44:51.355157", "detail": "1 trade, 1000 samples", "key": "XVA: Building cube", "progress": 800, "total": 1000 }
{ "@timestamp": "2026-03-15T13:44:51.603898", "detail": "1 trade, 1000 samples", "key": "XVA: Building cube", "progress": 810, "total": 1000 }
{ "@timestamp": "2026-03-15T13:44:51.851637", "detail": "1 trade, 1000 samples", "key": "XVA: Building cube", "progress": 820, "total": 1000 }
{ "@timestamp": "2026-03-15T13:44:52.099160", "detail": "1 trade, 1000 samples", "key": "XVA: Building cube", "progress": 830, "total": 1000 }
{ "@timestamp": "2026-03-15T13:44:52.346000", "detail": "1 trade, 1000 samples", "key": "XVA: Building cube", "progress": 840, "total": 1000 }
{ "@timestamp": "2026-03-15T13:44:52.593544", "detail": "1 trade, 1000 samples", "key": "XVA: Building cube", "progress": 850, "total": 1000 }
{ "@timestamp": "2026-03-15T13:44:52.841447", "detail": "1 trade, 1000 samples", "key": "XVA: Building cube", "progress": 860, "total": 1000 }
{ "@timestamp": "2026-03-15T13:44:53.090368", "detail": "1 trade, 1000 samples", "key": "XVA: Building cube", "progress": 870, "total": 1000 }
{ "@timestamp": "2026-03-15T13:44:53.339887", "detail": "1 trade, 1000 samples", "key": "XVA: Building cube", "progress": 880, "total": 1000 }
{ "@timestamp": "2026-03-15T13:44:53.587781", "detail": "1 trade, 1000 samples", "key": "XVA: Building cube", "progress": 890, "total": 1000 }
{ "@timestamp": "2026-03-15T13:44:53.836147", "detail": "1 trade, 1000 samples", "key": "XVA: Building cube", "progress": 900, "total": 1000 }
{ "@timestamp": "2026-03-15T13:44:54.084013", "detail": "1 trade, 1000 samples", "key": "XVA: Building cube", "progress": 910, "total": 1000 }
{ "@timestamp": "2026-03-15T13:44:54.332035", "detail": "1 trade, 1000 samples", "key": "XVA: Building cube", "progress": 920, "total": 1000 }
{ "@timestamp": "2026-03-15T13:44:54.579443", "detail": "1 trade, 1000 samples", "key": "XVA: Building cube", "progress": 930, "total": 1000 }
{ "@timestamp": "2026-03-15T13:44:54.828342", "detail": "1 trade, 1000 samples", "key": "XVA: Building cube", "progress": 940, "total": 1000 }
{ "@timestamp": "2026-03-15T13:44:55.075127", "detail": "1 trade, 1000 samples", "key": "XVA: Building cube", "progress": 950, "total": 1000 }
{ "@timestamp": "2026-03-15T13:44:55.324748", "detail": "1 trade, 1000 samples", "key": "XVA: Building cube", "progress": 960, "total": 1000 }
{ "@timestamp": "2026-03-15T13:44:55.574897", "detail": "1 trade, 1000 samples", "key": "XVA: Building cube", "progress": 970, "total": 1000 }
{ "@timestamp": "2026-03-15T13:44:55.824543", "detail": "1 trade, 1000 samples", "key": "XVA: Building cube", "progress": 980, "total": 1000 }
{ "@timestamp": "2026-03-15T13:44:56.072586", "detail": "1 trade, 1000 samples", "key": "XVA: Building cube", "progress": 990, "total": 1000 }
{ "@timestamp": "2026-03-15T13:44:56.295853", "detail": "1 trade, 1000 samples", "key": "XVA: Building cube", "progress": 1000, "total": 1000 }
{ "@timestamp": "2026-03-15T13:44:56.315891", "key": "XVA: Aggregation", "progress": 0, "total": 1 }
{ "@timestamp": "2026-03-15T13:45:22.487371", "key": "XVA: Aggregation", "progress": 1, "total": 1 }
{ "@timestamp": "2026-03-15T13:45:22.487507", "key": "XVA: Reports", "progress": 0, "total": 1 }
{ "@timestamp": "2026-03-15T13:45:22.505625", "key": "XVA: Reports", "progress": 1, "total": 1 }
{ "@timestamp": "2026-03-15T13:45:22.505779", "key": "Running XVA Analytic", "progress": 1, "total": 1 }
